README.md
setup.py
ino_vibe_sdk.egg-info/PKG-INFO
ino_vibe_sdk.egg-info/SOURCES.txt
ino_vibe_sdk.egg-info/dependency_links.txt
ino_vibe_sdk.egg-info/entry_points.txt
ino_vibe_sdk.egg-info/top_level.txt
inovibe/__init__.py
inovibe/log.py
inovibe/notification.py
test/test_log.py
test/test_log_for_unittest.py
test/test_notif.py