Metadata-Version: 1.0
Name: ino-vibe-sdk
Version: 0.1.1
Summary: Ino-Vibe SDK for Python
Home-page: UNKNOWN
Author: Joonkyo Kim
Author-email: jkkim@ino-on.com
License: UNKNOWN
Platform: UNKNOWN
